csv_admin/__init__.py
csv_admin/admin.py
csv_admin/apps.py
csv_admin/utils.py
csv_admin/locale/en/LC_MESSAGES/django.mo
csv_admin/locale/en/LC_MESSAGES/django.po
csv_admin/locale/ru/LC_MESSAGES/django.mo
csv_admin/locale/ru/LC_MESSAGES/django.po
csv_admin/locale/tk/LC_MESSAGES/django.mo
csv_admin/locale/tk/LC_MESSAGES/django.po
csv_admin/templates/csv_admin/add_csv_export_changelist.html
django_csv_admin-1.0.6.dist-info/LICENSE
django_csv_admin-1.0.6.dist-info/METADATA
django_csv_admin-1.0.6.dist-info/WHEEL
django_csv_admin-1.0.6.dist-info/top_level.txt
django_csv_admin-1.0.6.dist-info/RECORD
